tumorevolution/cell.py
tumorevolution/main.py
tumorevolution/simulation.py
tumorevolution/tissue.py
TumorEvolution-0.0.1.dist-info/LICENSE
TumorEvolution-0.0.1.dist-info/METADATA
TumorEvolution-0.0.1.dist-info/WHEEL
TumorEvolution-0.0.1.dist-info/top_level.txt
TumorEvolution-0.0.1.dist-info/RECORD
