Metadata-Version: 2.1
Name: TumorEvolution
Version: 0.0.1
Summary: Stochastic approach to compute tumor cells modelling
Home-page: https://github.com/neonicoo/tumor-evolution-modeling
Author: Nicolas Mendiboure
Author-email: nicolas.mendiboure@insa-lyon.fr
License: UNKNOWN
Platform: UNKNOWN
Classifier: Programming Language :: Python :: 3
Classifier: License :: OSI Approved :: MIT License
Classifier: Operating System :: OS Independent
Requires-Python: >=3.6
License-File: LICENSE
Requires-Dist: numpy
Requires-Dist: pandas
Requires-Dist: matplotlib
